aliyunsdkarms/__init__.py
aliyunsdkarms/endpoint.py
aliyunsdkarms/request/__init__.py
aliyunsdkarms/request/v20190808/AddAliClusterIdsToPrometheusGlobalViewRequest.py
aliyunsdkarms/request/v20190808/AddGrafanaRequest.py
aliyunsdkarms/request/v20190808/AddIntegrationRequest.py
aliyunsdkarms/request/v20190808/AddPrometheusGlobalViewByAliClusterIdsRequest.py
aliyunsdkarms/request/v20190808/AddPrometheusGlobalViewRequest.py
aliyunsdkarms/request/v20190808/AddPrometheusInstanceRequest.py
aliyunsdkarms/request/v20190808/AddPrometheusIntegrationRequest.py
aliyunsdkarms/request/v20190808/AddRecordingRuleRequest.py
aliyunsdkarms/request/v20190808/AddTagToFlinkClusterRequest.py
aliyunsdkarms/request/v20190808/AppendInstancesToPrometheusGlobalViewRequest.py
aliyunsdkarms/request/v20190808/ApplyScenarioRequest.py
aliyunsdkarms/request/v20190808/BindPrometheusGrafanaInstanceRequest.py
aliyunsdkarms/request/v20190808/BlockAlarmNotificationRequest.py
aliyunsdkarms/request/v20190808/ChangeAlarmSeverityRequest.py
aliyunsdkarms/request/v20190808/ChangeResourceGroupRequest.py
aliyunsdkarms/request/v20190808/CheckCommercialStatusRequest.py
aliyunsdkarms/request/v20190808/CheckServiceStatusRequest.py
aliyunsdkarms/request/v20190808/ClaimAlarmRequest.py
aliyunsdkarms/request/v20190808/CloseAlarmRequest.py
aliyunsdkarms/request/v20190808/ConfigAppRequest.py
aliyunsdkarms/request/v20190808/CreateAlertContactGroupRequest.py
aliyunsdkarms/request/v20190808/CreateAlertContactRequest.py
aliyunsdkarms/request/v20190808/CreateDispatchRuleRequest.py
aliyunsdkarms/request/v20190808/CreateEnvCustomJobRequest.py
aliyunsdkarms/request/v20190808/CreateEnvPodMonitorRequest.py
aliyunsdkarms/request/v20190808/CreateEnvServiceMonitorRequest.py
aliyunsdkarms/request/v20190808/CreateEnvironmentRequest.py
aliyunsdkarms/request/v20190808/CreateGrafanaWorkspaceRequest.py
aliyunsdkarms/request/v20190808/CreateIntegrationRequest.py
aliyunsdkarms/request/v20190808/CreateOrUpdateAlertRuleRequest.py
aliyun_python_sdk_arms-2.7.32.dist-info/LICENSE
aliyun_python_sdk_arms-2.7.32.dist-info/METADATA
aliyun_python_sdk_arms-2.7.32.dist-info/WHEEL
aliyun_python_sdk_arms-2.7.32.dist-info/top_level.txt
aliyun_python_sdk_arms-2.7.32.dist-info/RECORD
